MANIFEST.in
README.txt
pyresizeimage
setup.py
PyResizeImage.egg-info/PKG-INFO
PyResizeImage.egg-info/SOURCES.txt
PyResizeImage.egg-info/dependency_links.txt
PyResizeImage.egg-info/requires.txt
PyResizeImage.egg-info/top_level.txt
pyrszimg/COPYING.txt
pyrszimg/LEGGIMI.txt
pyrszimg/README.txt
pyrszimg/__init__.py
pyrszimg/core.py