Metadata-Version: 1.1
Name: PyResizeImage
Version: 0.9.6
Summary: Resize images, and pad them to give an exact size image
Home-page: https://launchpad.net/pyresizeimage
Author: Alkatron
Author-email: alkatron@gmail.com
License: GPLv3
Keywords: graphic,image,png,jpg,aspect ratio
Platform: UNKNOWN
Classifier: Programming Language :: Python
Classifier: Development Status :: 4 - Beta
Classifier: Environment :: Console
Classifier: Environment :: Other Environment
Classifier: Intended Audience :: Developers
Classifier: Intended Audience :: End Users/Desktop
Classifier: License :: OSI Approved :: GNU General Public License v3 (GPLv3)
Classifier: Operating System :: OS Independent
Classifier: Topic :: Software Development :: Libraries :: Python Modules
Classifier: Topic :: Multimedia :: Graphics :: Graphics Conversion
Classifier: Topic :: Multimedia :: Graphics
Classifier: Topic :: Utilities
